askharrison/SearchDatabase.py
askharrison/__init__.py
askharrison/arxiv_search.py
askharrison/change.py
askharrison/config.py
askharrison/google_search.py
askharrison/llm_models.py
askharrison/query_expansion.py
askharrison/arxiv_research/__init__.py
askharrison/prompts/__init__.py
askharrison/prompts/content_curation.py
askharrison/prompts/query_expansion.py
askharrison-0.1.1.dist-info/METADATA
askharrison-0.1.1.dist-info/WHEEL
askharrison-0.1.1.dist-info/top_level.txt
askharrison-0.1.1.dist-info/RECORD
