Metadata-Version: 2.1
Name: askharrison
Version: 0.1.1
Summary: A package for the AskHarrison, including various GenAI tools
Requires-Dist: streamlit
Requires-Dist: requests
Requires-Dist: pyarxiv
Requires-Dist: transformers
Requires-Dist: ipykernel
Requires-Dist: pandas
Requires-Dist: numpy
Requires-Dist: arxiv
Requires-Dist: openai==1.29.0
Requires-Dist: tiktoken
Requires-Dist: Pillow
